pprl/__init__.py
pprl/broker.py
pprl/encoder.py
pprl/match.py
pprl/model.py
pprl/schema.py
pprl/util.py
pprl-0.3.1.dist-info/LICENSE
pprl-0.3.1.dist-info/WHEEL
pprl-0.3.1.dist-info/METADATA
pprl-0.3.1.dist-info/RECORD
