Metadata-Version: 2.1
Name: pprl
Version: 0.3.1
Summary: Wrapper around PPRL services provided by MDS Group Leipzig
License: MIT
Author: Maximilian Jugl
Author-email: Maximilian.Jugl@medizin.uni-leipzig.de
Maintainer: Maximilian Jugl
Maintainer-email: Maximilian.Jugl@medizin.uni-leipzig.de
Requires-Python: >=3.10,<4.0
Classifier: Development Status :: 4 - Beta
Classifier: Intended Audience :: Developers
Classifier: Intended Audience :: Information Technology
Classifier: Intended Audience :: Science/Research
Classifier: License :: OSI Approved :: MIT License
Classifier: Natural Language :: English
Classifier: Operating System :: OS Independent
Classifier: Programming Language :: Python :: 3
Classifier: Programming Language :: Python :: 3.10
Classifier: Topic :: Scientific/Engineering :: Information Analysis
Classifier: Topic :: Security
Classifier: Typing :: Typed
Requires-Dist: requests (>=2.28.0,<3.0.0)
Project-URL: Documentation, https://pprl.gitlab.io/pprl-python-client/
